dai_python_commons/__init__.py
dai_python_commons/cdk_utils.py
dai_python_commons/cloudwatch_utils.py
dai_python_commons/dai_error.py
dai_python_commons/event_bridge.py
dai_python_commons/glue_utils.py
dai_python_commons/logging_utils.py
dai_python_commons/parquet_utils.py
dai_python_commons/s3_event_object_copy.py
dai_python_commons/s3_utils.py
dai_python_commons/time_utils.py
dai_python_commons-5.4.18.dist-info/METADATA
dai_python_commons-5.4.18.dist-info/WHEEL
dai_python_commons-5.4.18.dist-info/RECORD
