Metadata-Version: 2.1
Name: dai-python-commons
Version: 5.4.18
Summary: Collection of small python utilities useful for lambda functions or glue jobs. By the Stockholm Public Transport Administration.
Requires-Python: >=3.11,<3.12
Classifier: Programming Language :: Python :: 3
Classifier: Programming Language :: Python :: 3.11
Provides-Extra: data-consolidation
Provides-Extra: glue
Requires-Dist: awswrangler (==3.7.3) ; extra == "glue"
Requires-Dist: boto3 (>=1.34.63,<2.0.0)
Requires-Dist: boto3-stubs[glue,s3] (>=1.34.63,<2.0.0)
Requires-Dist: loguru (>=0.7.0,<0.8.0)
Requires-Dist: virtualenv (==20.27.1)
